Metadata-Version: 2.1
Name: scons-tool-loader
Version: 0.2.0
Summary: A little module that helps loading SCons tools installed via pip
Home-page: https://github.com/ptomulik/scons-tool-loader
Author: Paweł Tomulik
Author-email: ptomulik@meil.pw.edu.pl
License: UNKNOWN
Platform: UNKNOWN
